{
  "generated": "2026-06-11T05:29:28.979Z",
  "totalEntries": 76,
  "topicsExplored": [
    "system design patterns",
    "microservices architecture",
    "database optimization",
    "API design best practices",
    "authentication & authorization",
    "CI/CD pipelines",
    "containerization with Docker",
    "Kubernetes orchestration",
    "serverless computing",
    "GraphQL vs REST",
    "WebSocket real-time communication",
    "caching strategies",
    "message queues & event-driven design",
    "monitoring & observability"
  ],
  "activeDays": 10,
  "lastUpdate": "2026-06-11",
  "streak": 9
}